{"meta": {"code": 200, "requestId": "5d213e0e787dba0038dcddae"}, "response": {"warning": {"text": "There aren't a lot of results near you. Try something more general, reset your filters, or expand the search area."}, "headerLocation": "Bushwick", "headerFullLocation": "Bushwick, Brooklyn", "headerLocationGranularity": "neighborhood", "totalResults": 2, "suggestedBounds": {"ne": {"lat": 40.69471853534529, "lng": -73.91453806138277}, "sw": {"lat": 40.690218530845286, "lng": -73.92046193861724}}, "groups": [{"type": "Recommended Places", "name": "recommended", "items": [{"reasons": {"count": 0, "items": [{"summary": "This spot is popular", "type": "general", "reasonName": "globalInteractionReason"}]}, "venue": {"id": "59f4d1248c812a57e577a062", "name": "The Caffeine Underground", "location": {"address": "447 Central Ave", "crossStreet": "at Putnam Ave", "lat": 40.69217699029326, "lng": -73.9146619108384, "labeledLatLngs": [{"label": "display", "lat": 40.69217699029326, "lng": -73.9146619108384}], "distance": 241, "postalCode": "11221", "cc": "US", "city": "Brooklyn", "state": "NY", "country": "United States", "formattedAddress": ["447 Central Ave (at Putnam Ave)", "Brooklyn, NY 11221", "United States"]}, "categories": [{"id": "4bf58dd8d48988d1e0931735", "name": "Coffee Shop", "pluralName": "Coffee Shops", "shortName": "Coffee Shop", "icon": {"prefix": "https://ss3.4sqi.net/img/categories_v2/food/coffeeshop_", "suffix": ".png"}, "primary": true}], "photos": {"count": 0, "groups": []}}, "referralId": "e-0-59f4d1248c812a57e577a062-0"}, {"reasons": {"count": 0, "items": [{"summary": "This spot is popular", "type": "general", "reasonName": "globalInteractionReason"}]}, "venue": {"id": "4ba147fcf964a520c8a837e3", "name": "Williams Grocery", "location": {"lat": 40.692256, "lng": -73.919194, "labeledLatLngs": [{"label": "display", "lat": 40.692256, "lng": -73.919194}], "distance": 144, "postalCode": "11221", "cc": "US", "city": "Brooklyn", "state": "NY", "country": "United States", "formattedAddress": ["Brooklyn, NY 11221", "United States"]}, "categories": [{"id": "4bf58dd8d48988d146941735", "name": "Deli / Bodega", "pluralName": "Delis / Bodegas", "shortName": "Deli / Bodega", "icon": {"prefix": "https://ss3.4sqi.net/img/categories_v2/food/deli_", "suffix": ".png"}, "primary": true}], "photos": {"count": 0, "groups": []}}, "referralId": "e-0-4ba147fcf964a520c8a837e3-1"}]}]}}